limberer/__init__.py
limberer/pf.py
limberer/static/project.toml
limberer/static/assets/core.css
limberer/static/assets/logo.svg
limberer/static/assets/style.css
limberer/static/custom/custom.css
limberer/static/images/test1.jpg
limberer/static/sections/compositetable-text.md
limberer/static/sections/compositetableexample.md
limberer/static/sections/configexample.md
limberer/static/sections/configexample1.toml
limberer/static/sections/configexample2.json
limberer/static/sections/configexample3.xml
limberer/static/sections/configexample4.csv
limberer/static/sections/configexample5.dcsv
limberer/static/sections/configexample6.ncsv
limberer/static/sections/csvexample.md
limberer/static/sections/dcsvexample.md
limberer/static/sections/example.md
limberer/static/sections/example2.md
limberer/static/sections/example3.md
limberer/static/sections/ncsvexample.md
limberer/static/sections/xmlexample.md
limberer/static/templates/base.html
limberer/static/templates/cover.html
limberer/static/templates/section.html
limberer/static/templates/toc.html
limberer-0.9.2.dist-info/AUTHORS
limberer-0.9.2.dist-info/LICENSE
limberer-0.9.2.dist-info/METADATA
limberer-0.9.2.dist-info/WHEEL
limberer-0.9.2.dist-info/entry_points.txt
limberer-0.9.2.dist-info/top_level.txt
limberer-0.9.2.dist-info/RECORD
