Metadata-Version: 2.2
Name: limberer
Version: 0.9.2
Summary: A flexible document generator based on weasyprint, mustache templates, and pandoc.
Author-email: Jeff Dileo <jtdileo@gmail.com>
Maintainer-email: Jeff Dileo <jtdileo@gmail.com>
License: Copyright (c) 2023 Jeff Dileo.
Project-URL: repository, https://github.com/ChaosData/limberer
Keywords: pandoc,panflute,markdown,html,pdf,report,document,generator
Classifier: License :: OSI Approved :: BSD License
Classifier: Programming Language :: Python :: 3.9
Requires-Python: >=3.9
License-File: LICENSE
License-File: AUTHORS
Requires-Dist: panflute
Requires-Dist: chevron
Requires-Dist: weasyprint
Requires-Dist: rtoml
Requires-Dist: pillow
Requires-Dist: beautifulsoup4
Requires-Dist: Pygments
